rustimport_jupyter/__init__.py
rustimport_jupyter/_ipython_magic.py
rustimport_jupyter/_version.py
rustimport_jupyter-0.1.3.dist-info/METADATA
rustimport_jupyter-0.1.3.dist-info/WHEEL
rustimport_jupyter-0.1.3.dist-info/licenses/LICENSE
rustimport_jupyter-0.1.3.dist-info/RECORD
