Metadata-Version: 2.1
Name: rustimport_jupyter
Version: 0.1.3
Summary: Jupyter and IPython magic for compiling Python extensions written in Rust
Project-URL: Source, https://github.com/thomasjpfan/rustimport_jupyter
Author-email: "Thomas J. Fan" <thomasjpfan@gmail.com>
License-Expression: MIT
License-File: LICENSE
Classifier: Development Status :: 4 - Beta
Classifier: Programming Language :: Python
Classifier: Programming Language :: Python :: 3.8
Classifier: Programming Language :: Python :: 3.9
Classifier: Programming Language :: Python :: 3.10
Classifier: Programming Language :: Python :: 3.11
Classifier: Programming Language :: Python :: 3.12
Classifier: Programming Language :: Python :: Implementation :: CPython
Classifier: Programming Language :: Python :: Implementation :: PyPy
Requires-Python: >=3.8
Requires-Dist: ipython
Requires-Dist: rustimport
